{
    "$schema": "https://shadcn-svelte.com/schema/registry.json",
    "name": "shadcn-svelte",
    "homepage": "https://adv76.github.io/kibo-svelte",
    "aliases": {
		"lib": "$lib/registry/lib",
		"ui": "$lib/registry/ui",
		"components": "./components",
		"utils": "$lib/utils",
		"hooks": "$lib/registry/hooks"
	},
    "items": [
        {
            "name": "announcement",
            "type": "registry:ui",
            "title": "Announcement",
            "description": "A compound badge designed to display an announcement.",
            "registryDependencies": ["badge"],
            "files": [
                {
                    "path": "src/lib/registry/components/announcement/announcement.svelte",
                    "type": "registry:file",
                    "target": "../kibo-ui/announcement/announcement.svelte"
                },
                {
                    "path": "src/lib/registry/components/announcement/announcement-tag.svelte",
                    "type": "registry:file",
                    "target": "../kibo-ui/announcement/announcement-tag.svelte"
                },
                {
                    "path": "src/lib/registry/components/announcement/announcement-title.svelte",
                    "type": "registry:file",
                    "target": "../kibo-ui/announcement/announcement-title.svelte"
                },
                {
                    "path": "src/lib/registry/components/announcement/index.ts",
                    "type": "registry:file",
                    "target": "../kibo-ui/announcement/index.ts"
                }
            ]
        },
        {
            "name": "avatar-stack",
            "type": "registry:ui",
            "title": "Avatar Stack",
            "description": "Avatar Stack is a component that allows you to stack and overlap avatars.",
            "registryDependencies": ["avatar"],
            "files": [
                {
                    "path": "src/lib/registry/components/avatar-stack/avatar-stack.svelte",
                    "type": "registry:file",
                    "target": "../kibo-ui/avatar-stack/avatar-stack.svelte"
                },
                {
                    "path": "src/lib/registry/components/avatar-stack/avatar-stack-avatar.svelte",
                    "type": "registry:file",
                    "target": "../kibo-ui//avatar-stack/avatar-stack-avatar.svelte"
                },
                {
                    "path": "src/lib/registry/components/avatar-stack/index.ts",
                    "type": "registry:file",
                    "target": "../kibo-ui/avatar-stack/index.ts"
                }
            ]
        },
        {
            "name": "banner",
            "type": "registry:ui",
            "title": "Banner",
            "description": "A banner is a full-width component that can be used to show a message and action to the user.",
            "devDependencies": ["@lucide/svelte"],
            "registryDependencies": ["button"],
            "files": [
                {
                    "path": "src/lib/registry/components/banner/banner.svelte",
                    "type": "registry:file",
                    "target": "../kibo-ui/banner/banner.svelte"
                },
                {
                    "path": "src/lib/registry/components/banner/banner-action.svelte",
                    "type": "registry:file",
                    "target": "../kibo-ui/banner/banner-action.svelte"
                },
                {
                    "path": "src/lib/registry/components/banner/banner-close.svelte",
                    "type": "registry:file",
                    "target": "../kibo-ui/banner/banner-close.svelte"
                },
                {
                    "path": "src/lib/registry/components/banner/banner-context.svelte.ts",
                    "type": "registry:file",
                    "target": "../kibo-ui/banner/banner-context.svelte.ts"
                },
                {
                    "path": "src/lib/registry/components/banner/banner-icon.svelte",
                    "type": "registry:file",
                    "target": "../kibo-ui/banner/banner-icon.svelte"
                },
                {
                    "path": "src/lib/registry/components/banner/banner-title.svelte",
                    "type": "registry:file",
                    "target": "../kibo-ui/banner/banner-title.svelte"
                },
                {
                    "path": "src/lib/registry/components/banner/index.ts",
                    "type": "registry:file",
                    "target": "../kibo-ui/banner/index.ts"
                }
            ]
        },
        {
            "name": "choicebox",
            "type": "registry:ui",
            "title": "Choicebox",
            "description": "Choiceboxes are a great way to show radio or checkbox options with a card style.",
            "registryDependencies": ["field", "radio-group"],
            "files": [
                {
                    "path": "src/lib/registry/components/choicebox/choicebox-context.svelte.ts",
                    "type": "registry:file",
                    "target": "../kibo-ui/choicebox/choicebox-context.svelte.ts"
                },
                {
                    "path": "src/lib/registry/components/choicebox/choicebox.svelte",
                    "type": "registry:file",
                    "target": "../kibo-ui/choicebox/choicebox.svelte"
                },
                {
                    "path": "src/lib/registry/components/choicebox/choicebox-indicator.svelte",
                    "type": "registry:file",
                    "target": "../kibo-ui/choicebox/choicebox-indicator.svelte"
                },
                {
                    "path": "src/lib/registry/components/choicebox/choicebox-item.svelte",
                    "type": "registry:file",
                    "target": "../kibo-ui/choicebox/choicebox-item.svelte"
                },
                {
                    "path": "src/lib/registry/components/choicebox/choicebox-item-description.svelte",
                    "type": "registry:file",
                    "target": "../kibo-ui/choicebox/choicebox-item-description.svelte"
                },
                {
                    "path": "src/lib/registry/components/choicebox/choicebox-item-header.svelte",
                    "type": "registry:file",
                    "target": "../kibo-ui/choicebox/choicebox-item-header.svelte"
                },
                {
                    "path": "src/lib/registry/components/choicebox/choicebox-item-subtitle.svelte",
                    "type": "registry:file",
                    "target": "../kibo-ui/choicebox/choicebox-item-subtitle.svelte"
                },
                {
                    "path": "src/lib/registry/components/choicebox/choicebox-item-title.svelte",
                    "type": "registry:file",
                    "target": "../kibo-ui/choicebox/choicebox-item-title.svelte"
                },
                {
                    "path": "src/lib/registry/components/choicebox/index.ts",
                    "type": "registry:file",
                    "target": "../kibo-ui/choicebox/index.ts"
                }
            ]
        },
        {
            "name": "code-block",
            "type": "registry:ui",
            "title": "Code Block",
            "description": "Provides syntax highlighting, line numbers, and copy to clipboard functionality for code blocks.",
            "devDependencies": ["@lucide/svelte", "shiki"],
            "registryDependencies": ["button", "select"],
            "files": [
                {
                    "path": "src/lib/registry/components/code-block/class-names.ts",
                    "type": "registry:file",
                    "target": "../kibo-ui/announcement/index.ts"
                },
                {
                    "path": "src/lib/registry/components/code-block/code-block.svelte",
                    "type": "registry:file",
                    "target": "../kibo-ui/code-block/code-block.svelte"
                },
                {
                    "path": "src/lib/registry/components/code-block/code-block-body.svelte",
                    "type": "registry:file",
                    "target": "../kibo-ui/code-block/code-block-body.svelte"
                },
                {
                    "path": "src/lib/registry/components/code-block/code-block-content.svelte",
                    "type": "registry:file",
                    "target": "../kibo-ui/code-block/code-block-content.svelte"
                },
                {
                    "path": "src/lib/registry/components/code-block/code-block-context.svelte.ts",
                    "type": "registry:file",
                    "target": "../kibo-ui/code-block/code-block-context.svelte.ts"
                },
                {
                    "path": "src/lib/registry/components/code-block/code-block-copy-button.svelte",
                    "type": "registry:file",
                    "target": "../kibo-ui/code-block/code-block-copy-button.svelte"
                },
                {
                    "path": "src/lib/registry/components/code-block/code-block-fallback.svelte",
                    "type": "registry:file",
                    "target": "../kibo-ui/code-block/code-block-fallback.svelte"
                },
                {
                    "path": "src/lib/registry/components/code-block/code-block-filename.svelte",
                    "type": "registry:file",
                    "target": "../kibo-ui/code-block/code-block-filename.svelte"
                },
                {
                    "path": "src/lib/registry/components/code-block/code-block-files.svelte",
                    "type": "registry:file",
                    "target": "../kibo-ui/code-block/code-block-files.svelte"
                },
                {
                    "path": "src/lib/registry/components/code-block/code-block-header.svelte",
                    "type": "registry:file",
                    "target": "../kibo-ui/code-block/code-block-header.svelte"
                },
                {
                    "path": "src/lib/registry/components/code-block/code-block-item.svelte",
                    "type": "registry:file",
                    "target": "../kibo-ui/code-block/code-block-item.svelte"
                },
                {
                    "path": "src/lib/registry/components/code-block/code-block-select.svelte",
                    "type": "registry:file",
                    "target": "../kibo-ui/code-block/code-block-select.svelte"
                },
                {
                    "path": "src/lib/registry/components/code-block/code-block-select-content.svelte",
                    "type": "registry:file",
                    "target": "../kibo-ui/code-block/code-block-select-content.svelte"
                },
                {
                    "path": "src/lib/registry/components/code-block/code-block-select-item.svelte",
                    "type": "registry:file",
                    "target": "../kibo-ui/code-block/code-block-select-item.svelte"
                },
                {
                    "path": "src/lib/registry/components/code-block/code-block-select-trigger.svelte",
                    "type": "registry:file",
                    "target": "../kibo-ui/code-block/code-block-select-trigger.svelte"
                },
                {
                    "path": "src/lib/registry/components/code-block/code-block-select-value.svelte",
                    "type": "registry:file",
                    "target": "../kibo-ui/code-block/code-block-select-value.svelte"
                },
                {
                    "path": "src/lib/registry/components/code-block/index.ts",
                    "type": "registry:file",
                    "target": "../kibo-ui/code-block/index.ts"
                },
                {
                    "path": "src/lib/registry/components/code-block/types.ts",
                    "type": "registry:file",
                    "target": "../kibo-ui/code-block/types.ts"
                }
            ]
        },
        {
            "name": "color-picker",
            "type": "registry:ui",
            "title": "Color Picker",
            "description": "Allows users to select a color. Modeled after the color picker in Figma.",
            "dependencies": ["color"],
            "devDependencies": ["bits-ui", "@lucide/svelte"],
            "registryDependencies": ["button", "input", "select"],
            "files": [
                {
                    "path": "src/lib/registry/components/color-picker/color-picker.svelte",
                    "type": "registry:file",
                    "target": "../kibo-ui/color-picker/color-picker.svelte"
                },
                {
                    "path": "src/lib/registry/components/color-picker/color-picker-alpha.svelte",
                    "type": "registry:file",
                    "target": "../kibo-ui/color-picker/color-picker-alpha.svelte"
                },
                {
                    "path": "src/lib/registry/components/color-picker/color-picker-context.svelte.ts",
                    "type": "registry:file",
                    "target": "../kibo-ui/color-picker/color-picker-context.svelte.ts"
                },
                {
                    "path": "src/lib/registry/components/color-picker/color-picker-eye-dropper.svelte",
                    "type": "registry:file",
                    "target": "../kibo-ui/color-picker/color-picker-eye-dropper.svelte"
                },
                {
                    "path": "src/lib/registry/components/color-picker/color-picker-format.svelte",
                    "type": "registry:file",
                    "target": "../kibo-ui/color-picker/color-picker-format.svelte"
                },
                {
                    "path": "src/lib/registry/components/color-picker/color-picker-hue.svelte",
                    "type": "registry:file",
                    "target": "../kibo-ui/color-picker/color-picker-hue.svelte"
                },
                {
                    "path": "src/lib/registry/components/color-picker/color-picker-output.svelte",
                    "type": "registry:file",
                    "target": "../kibo-ui/color-picker/color-picker-output.svelte"
                },
                {
                    "path": "src/lib/registry/components/color-picker/color-picker-percentage-input.svelte",
                    "type": "registry:file",
                    "target": "../kibo-ui/color-picker/color-picker-percentage-input.svelte"
                },
                {
                    "path": "src/lib/registry/components/color-picker/color-picker-selection.svelte",
                    "type": "registry:file",
                    "target": "../kibo-ui/color-picker/color-picker-selection.svelte"
                },
                {
                    "path": "src/lib/registry/components/color-picker/index.ts",
                    "type": "registry:file",
                    "target": "../kibo-ui/color-picker/index.ts"
                }
            ]
        },
        {
            "name": "contribution-graph",
            "type": "registry:ui",
            "title": "Contribution Graph",
            "description": "A GitHub-style contribution graph component that displays activity levels over time.",
            "dependencies": ["date-fns"],
            "registryDependencies": ["button", "input", "select"],
            "files": [
                {
                    "path": "src/lib/registry/components/contribution-graph/contribution-graph.svelte",
                    "type": "registry:file",
                    "target": "../kibo-ui/contribution-graph/contribution-graph.svelte"
                },
                {
                    "path": "src/lib/registry/components/contribution-graph/contribution-graph-block.svelte",
                    "type": "registry:file",
                    "target": "../kibo-ui/contribution-graph/contribution-graph-block.svelte"
                },
                {
                    "path": "src/lib/registry/components/contribution-graph/contribution-graph-calendar.svelte",
                    "type": "registry:file",
                    "target": "../kibo-ui/contribution-graph/contribution-graph-calendar.svelte"
                },
                {
                    "path": "src/lib/registry/components/contribution-graph/contribution-graph-context.svelte.ts",
                    "type": "registry:file",
                    "target": "../kibo-ui/contribution-graph/contribution-graph-context.svelte.ts"
                },
                {
                    "path": "src/lib/registry/components/contribution-graph/contribution-graph-footer.svelte",
                    "type": "registry:file",
                    "target": "../kibo-ui/contribution-graph/contribution-graph-footer.svelte"
                },
                {
                    "path": "src/lib/registry/components/contribution-graph/contribution-graph-legend.svelte",
                    "type": "registry:file",
                    "target": "../kibo-ui/contribution-graph/contribution-graph-legend.svelte"
                },
                {
                    "path": "src/lib/registry/components/contribution-graph/contribution-graph-total-count.svelte",
                    "type": "registry:file",
                    "target": "../kibo-ui/contribution-graph/contribution-graph-total-count.svelte"
                },
                {
                    "path": "src/lib/registry/components/contribution-graph/index.ts",
                    "type": "registry:file",
                    "target": "../kibo-ui/contribution-graph/index.ts"
                },
                {
                    "path": "src/lib/registry/components/contribution-graph/types.ts",
                    "type": "registry:file",
                    "target": "../kibo-ui/contribution-graph/types.ts"
                },
                {
                    "path": "src/lib/registry/components/contribution-graph/utils.ts",
                    "type": "registry:file",
                    "target": "../kibo-ui/contribution-graph/utils.ts"
                }
            ]
        },
        {
            "name": "cursor",
            "type": "registry:ui",
            "title": "Cursor",
            "description": "A cursor component, great for realtime interactive applications.",
            "registryDependencies": [],
            "files": [
                {
                    "path": "src/lib/registry/components/cursor/cursor.svelte",
                    "type": "registry:file",
                    "target": "../kibo-ui/cursor/cursor.svelte"
                },
                {
                    "path": "src/lib/registry/components/cursor/cursor-body.svelte",
                    "type": "registry:file",
                    "target": "../kibo-ui/cursor/cursor-body.svelte"
                },
                {
                    "path": "src/lib/registry/components/cursor/cursor-message.svelte",
                    "type": "registry:file",
                    "target": "../kibo-ui/cursor/cursor-message.svelte"
                },
                {
                    "path": "src/lib/registry/components/cursor/cursor-name.svelte",
                    "type": "registry:file",
                    "target": "../kibo-ui/cursor/cursor-name.svelte"
                },
                {
                    "path": "src/lib/registry/components/cursor/cursor-pointer.svelte",
                    "type": "registry:file",
                    "target": "../kibo-ui/cursor/cursor-pointer.svelte"
                },
                {
                    "path": "src/lib/registry/components/cursor/index.ts",
                    "type": "registry:file",
                    "target": "../kibo-ui/cursor/index.ts"
                }
            ]
        },
        {
            "name": "image-zoom",
            "type": "registry:ui",
            "title": "Image Zoom",
            "description": "Image zoom is a component that allows you to zoom in on an image.",
            "dependencies": ["svelte-medium-image-zoom"],
            "registryDependencies": [],
            "files": [
                {
                    "path": "src/lib/registry/components/image-zoom/image-zoom.svelte",
                    "type": "registry:file",
                    "target": "../kibo-ui/image-zoom/image-zoom.svelte"
                },
                {
                    "path": "src/lib/registry/components/image-zoom/index.ts",
                    "type": "registry:file",
                    "target": "../kibo-ui/image-zoom/index.ts"
                }
            ]
        },
        {
            "name": "kanban",
            "type": "registry:ui",
            "title": "Kanban",
            "description": "A kanban board is a visual tool that helps you manage and visualize your work. It is a board with columns, and each column represents a status, e.g. \"Backlog\", \"In Progress\", \"Done\".",
            "dependencies": ["@dnd-kit-svelte/core", "@dnd-kit-svelte/sortable", "@dnd-kit-svelte/svelte", "@dnd-kit-svelte/utilities"],
            "devDependencies": ["bits-ui"],
            "registryDependencies": ["card", "scroll-area"],
            "files": [
                {
                    "path": "src/lib/registry/components/kanban/kanban-board.svelte",
                    "type": "registry:file",
                    "target": "../kibo-ui/kanban/kanban-board.svelte"
                },
                {
                    "path": "src/lib/registry/components/kanban/kanban-card.svelte",
                    "type": "registry:file",
                    "target": "../kibo-ui/kanban/kanban-card.svelte"
                },
                {
                    "path": "src/lib/registry/components/kanban/kanban-cards.svelte",
                    "type": "registry:file",
                    "target": "../kibo-ui/kanban/kanban-cards.svelte"
                },
                {
                    "path": "src/lib/registry/components/kanban/kanban-header.svelte",
                    "type": "registry:file",
                    "target": "../kibo-ui/kanban/kanban-header.svelte"
                },
                {
                    "path": "src/lib/registry/components/kanban/kanban-provider.svelte",
                    "type": "registry:file",
                    "target": "../kibo-ui/kanban/kanban-provider.svelte"
                },
                {
                    "path": "src/lib/registry/components/kanban/kanban-context.svelte.ts",
                    "type": "registry:file",
                    "target": "../kibo-ui/kanban/kanban-context.svelte.ts"
                },
                {
                    "path": "src/lib/registry/components/kanban/types.ts",
                    "type": "registry:file",
                    "target": "../kibo-ui/kanban/types.ts"
                },
                {
                    "path": "src/lib/registry/components/kanban/index.ts",
                    "type": "registry:file",
                    "target": "../kibo-ui/kanban/index.ts"
                }
            ]
        },
        {
            "name": "marquee",
            "type": "registry:ui",
            "title": "Marquee",
            "description": "Marquees are a great way to show a list of items in a horizontal scrolling motion.",
            "dependencies": ["@selemondev/svelte-marquee"],
            "registryDependencies": [],
            "files": [
                {
                    "path": "src/lib/registry/components/marquee/marquee.svelte",
                    "type": "registry:file",
                    "target": "../kibo-ui/marquee/marquee.svelte"
                },
                {
                    "path": "src/lib/registry/components/marquee/marquee-content.svelte",
                    "type": "registry:file",
                    "target": "../kibo-ui/marquee/marquee-content.svelte"
                },
                {
                    "path": "src/lib/registry/components/marquee/marquee-item.svelte",
                    "type": "registry:file",
                    "target": "../kibo-ui/marquee/marquee-item.svelte"
                },
                {
                    "path": "src/lib/registry/components/marquee/index.ts",
                    "type": "registry:file",
                    "target": "../kibo-ui/marquee/index.ts"
                }
            ]
        },
        {
            "name": "pill",
            "type": "registry:ui",
            "title": "Pill",
            "description": "A flexible badge component designed for a variety of use cases.",
            "devDependencies": ["@lucide/svelte"],
            "registryDependencies": ["avatar", "badge", "button"],
            "files": [
                {
                    "path": "src/lib/registry/components/pill/pill.svelte",
                    "type": "registry:file",
                    "target": "../kibo-ui/pill/pill.svelte"
                },
                {
                    "path": "src/lib/registry/components/pill/pill-avatar.svelte",
                    "type": "registry:file",
                    "target": "../kibo-ui/pill/pill-avatar.svelte"
                },
                {
                    "path": "src/lib/registry/components/pill/pill-avatar-group.svelte",
                    "type": "registry:file",
                    "target": "../kibo-ui/pill/pill-avatar-group.svelte"
                },
                {
                    "path": "src/lib/registry/components/pill/pill-button.svelte",
                    "type": "registry:file",
                    "target": "../kibo-ui/pill/pill-button.svelte"
                },
                {
                    "path": "src/lib/registry/components/pill/pill-delta.svelte",
                    "type": "registry:file",
                    "target": "../kibo-ui/pill/pill-delta.svelte"
                },
                {
                    "path": "src/lib/registry/components/pill/pill-icon.svelte",
                    "type": "registry:file",
                    "target": "../kibo-ui/pill/pill-icon.svelte"
                },
                {
                    "path": "src/lib/registry/components/pill/pill-indicator.svelte",
                    "type": "registry:file",
                    "target": "../kibo-ui/pill/pill-indicator.svelte"
                },
                {
                    "path": "src/lib/registry/components/pill/pill-status.svelte",
                    "type": "registry:file",
                    "target": "../kibo-ui/pill/pill-status.svelte"
                },
                {
                    "path": "src/lib/registry/components/pill/index.ts",
                    "type": "registry:file",
                    "target": "../kibo-ui/pill/index.ts"
                }
            ]
        },
        {
            "name": "qr-code",
            "type": "registry:ui",
            "title": "QR Code",
            "description": "QR Code is a component that generates a QR code from a string.",
            "dependencies": ["culori", "qrcode"],
            "registryDependencies": [],
            "files": [
                {
                    "path": "src/lib/registry/components/qr-code/qr-code.svelte",
                    "type": "registry:file",
                    "target": "../kibo-ui/qr-code/qr-code.svelte"
                },
                {
                    "path": "src/lib/registry/components/qr-code/index.ts",
                    "type": "registry:file",
                    "target": "../kibo-ui/qr-code/index.ts"
                }
            ]
        },
        {
            "name": "snippet",
            "type": "registry:ui",
            "title": "Snippet",
            "description": "Snippet is a component that allows you to display and copy code in a tabbed interface.",
            "registryDependencies": ["button", "tabs"],
            "files": [
                {
                    "path": "src/lib/registry/components/snippet/snippet.svelte",
                    "type": "registry:file",
                    "target": "../kibo-ui/snippet/snippet.svelte"
                },
                {
                    "path": "src/lib/registry/components/snippet/snippet-copy-button.svelte",
                    "type": "registry:file",
                    "target": "../kibo-ui/snippet/snippet-copy-button.svelte"
                },
                {
                    "path": "src/lib/registry/components/snippet/snippet-header.svelte",
                    "type": "registry:file",
                    "target": "../kibo-ui/snippet/snippet-header.svelte"
                },
                {
                    "path": "src/lib/registry/components/snippet/snippet-tabs-content.svelte",
                    "type": "registry:file",
                    "target": "../kibo-ui/snippet/snippet-tabs-content.svelte"
                },
                {
                    "path": "src/lib/registry/components/snippet/snippet-tabs-trigger.svelte",
                    "type": "registry:file",
                    "target": "../kibo-ui/snippet/snippet-tabs-trigger.svelte"
                },
                {
                    "path": "src/lib/registry/components/snippet/index.ts",
                    "type": "registry:file",
                    "target": "../kibo-ui/snippet/index.ts"
                }
            ]
        },
        {
            "name": "spinner",
            "type": "registry:ui",
            "title": "Spinner",
            "description": "The Spinner component expands the shadcn spinner component with additional variants.",
            "devDependencies": ["@lucide/svelte"],
            "registryDependencies": ["spinner"],
            "files": [
                {
                    "path": "src/lib/registry/components/spinner/spinner.svelte",
                    "type": "registry:file",
                    "target": "../kibo-ui/spinner/spinner.svelte"
                },
                {
                    "path": "src/lib/registry/components/spinner/spinners/bars.svelte",
                    "type": "registry:file",
                    "target": "../kibo-ui/spinner/spinners/bars.svelte"
                },
                {
                    "path": "src/lib/registry/components/spinner/spinners/circle-filled.svelte",
                    "type": "registry:file",
                    "target": "../kibo-ui/spinner/spinners/circle-filled.svelte"
                },
                {
                    "path": "src/lib/registry/components/spinner/spinners/ellipsis.svelte",
                    "type": "registry:file",
                    "target": "../kibo-ui/spinner/spinners/ellipsis.svelte"
                },
                {
                    "path": "src/lib/registry/components/spinner/spinners/infinite.svelte",
                    "type": "registry:file",
                    "target": "../kibo-ui/spinner/spinners/infinite.svelte"
                },
                {
                    "path": "src/lib/registry/components/spinner/spinners/pinwheel.svelte",
                    "type": "registry:file",
                    "target": "../kibo-ui/spinner/spinners/pinwheel.svelte"
                },
                {
                    "path": "src/lib/registry/components/spinner/spinners/ring.svelte",
                    "type": "registry:file",
                    "target": "../kibo-ui/spinner/spinners/ring.svelte"
                },
                {
                    "path": "src/lib/registry/components/spinner/spinners/throbber.svelte",
                    "type": "registry:file",
                    "target": "../kibo-ui/spinner/spinners/throbber.svelte"
                },
                {
                    "path": "src/lib/registry/components/spinner/index.ts",
                    "type": "registry:file",
                    "target": "../kibo-ui/spinner/index.ts"
                },
                {
                    "path": "src/lib/registry/components/spinner/types.ts",
                    "type": "registry:file",
                    "target": "../kibo-ui/spinner/types.ts"
                }
            ]
        },
        {
            "name": "status",
            "type": "registry:ui",
            "title": "Status",
            "description": "Status components are used to display the uptime of a service.",
            "registryDependencies": ["badge"],
            "files": [
                {
                    "path": "src/lib/registry/components/status/status.svelte",
                    "type": "registry:file",
                    "target": "../kibo-ui/status/status.svelte"
                },
                {
                    "path": "src/lib/registry/components/status/status-label.svelte",
                    "type": "registry:file",
                    "target": "../kibo-ui/status/status-label.svelte"
                },
                {
                    "path": "src/lib/registry/components/status/status-indicator.svelte",
                    "type": "registry:file",
                    "target": "../kibo-ui/status/status-indicator.svelte"
                },
                {
                    "path": "src/lib/registry/components/status/index.ts",
                    "type": "registry:file",
                    "target": "../kibo-ui/status/index.ts"
                }
            ]
        },
        {
            "name": "stories",
            "type": "registry:ui",
            "title": "Stories",
            "description": "A carousel of friends' stories, in video, image or avatar format.",
            "registryDependencies": ["avatar", "carousel"],
            "files": [
                {
                    "path": "src/lib/registry/components/stories/stories.svelte",
                    "type": "registry:file",
                    "target": "../kibo-ui/stories/stories.svelte"
                },
                {
                    "path": "src/lib/registry/components/stories/stories-content.svelte",
                    "type": "registry:file",
                    "target": "../kibo-ui/stories/stories-content.svelte"
                },
                {
                    "path": "src/lib/registry/components/stories/story.svelte",
                    "type": "registry:file",
                    "target": "../kibo-ui/stories/story.svelte"
                },
                {
                    "path": "src/lib/registry/components/stories/story-author.svelte",
                    "type": "registry:file",
                    "target": "../kibo-ui/stories/story-author.svelte"
                },
                {
                    "path": "src/lib/registry/components/stories/story-author-image.svelte",
                    "type": "registry:file",
                    "target": "../kibo-ui/stories/story-author-image.svelte"
                },
                {
                    "path": "src/lib/registry/components/stories/story-author-name.svelte",
                    "type": "registry:file",
                    "target": "../kibo-ui/stories/story-author-name.svelte"
                },
                {
                    "path": "src/lib/registry/components/stories/story-image.svelte",
                    "type": "registry:file",
                    "target": "../kibo-ui/stories/story-image.svelte"
                },
                {
                    "path": "src/lib/registry/components/stories/story-overlay.svelte",
                    "type": "registry:file",
                    "target": "../kibo-ui/stories/story-overlay.svelte"
                },
                {
                    "path": "src/lib/registry/components/stories/story-title.svelte",
                    "type": "registry:file",
                    "target": "../kibo-ui/stories/story-title.svelte"
                },
                {
                    "path": "src/lib/registry/components/stories/story-video.svelte",
                    "type": "registry:file",
                    "target": "../kibo-ui/stories/story-video.svelte"
                },
                {
                    "path": "src/lib/registry/components/stories/index.ts",
                    "type": "registry:file",
                    "target": "../kibo-ui/stories/index.ts"
                }
            ]
        },
        {
            "name": "theme-switcher",
            "type": "registry:ui",
            "title": "Theme Switcher",
            "description": "A component to switch between light, dark and system theme.",
            "devDependencies": ["@lucide/svelte"],
            "registryDependencies": [],
            "files": [
                {
                    "path": "src/lib/registry/components/theme-switcher/theme-switcher.svelte",
                    "type": "registry:file",
                    "target": "../kibo-ui/theme-switcher/theme-switcher.svelte"
                },
                {
                    "path": "src/lib/registry/components/theme-switcher/index.ts",
                    "type": "registry:file",
                    "target": "../kibo-ui/theme-switcher/index.ts"
                }
            ]
        },
        {
            "name": "typography",
            "type": "registry:ui",
            "title": "typography",
            "description": "A component for applying consistent typography styles across your application.",
            "registryDependencies": [],
            "files": [
                {
                    "path": "src/lib/registry/components/typography/styles.css",
                    "type": "registry:file",
                    "target": "../kibo-ui/typography/styles.css"
                }
            ]
        }
    ]
}